metaloader/__init__.py
metaloader/exceptions.py
metaloader/flat_loader.py
metaloader/loader_context.py
metaloader/directives/__init__.py
metaloader/directives/directive.py
metaloader/directives/imports.py
metaloader/filesystems/__init__.py
metaloader/filesystems/filesystem.py
metaloader/filesystems/local.py
metaloader/filesystems/virtual.py
metaloader/serialisations/__init__.py
metaloader/serialisations/json.py
metaloader/serialisations/serialisation.py
metaloader/serialisations/yaml.py
metaloader/stanzahandlers/__init__.py
metaloader/stanzahandlers/dict.py
metaloader/stanzahandlers/list.py
metaloader/stanzahandlers/stanza_handler.py
metaloader-0.4.0.dist-info/LICENSE
metaloader-0.4.0.dist-info/METADATA
metaloader-0.4.0.dist-info/WHEEL
metaloader-0.4.0.dist-info/top_level.txt
metaloader-0.4.0.dist-info/RECORD
