Metadata-Version: 2.1
Name: metaloader
Version: 0.4.0
Summary: A configurable pipeline for loading data files
Home-page: https://github.com/jacobneiltaylor/metaloader
Author: Jacob Neil Taylor
Author-email: me@jacobtaylor.id.au
License: UNKNOWN
Platform: UNKNOWN
Classifier: Programming Language :: Python :: 3
Classifier: License :: OSI Approved :: MIT License
Classifier: Operating System :: OS Independent
Requires-Python: >=3.7
Requires-Dist: ruamel.yaml
Requires-Dist: plugable
